{
  "version": "2026-04-05",
  "rinks": [
    {
      "rink_id": "dc_medstar",
      "name": "MedStar Capitals Iceplex",
      "region": "DC Metro",
      "platform": "daysmart",
      "platform_code": "DS1",
      "scraper_file": "api/schedule.js",
      "company": "capitals",
      "status": "live",
      "priority": "P1"
    },
    {
      "rink_id": "dc_skatequest",
      "name": "SkateQuest",
      "region": "DC Metro",
      "platform": "daysmart",
      "platform_code": "DS1",
      "scraper_file": "api/schedule.js",
      "company": "skatequest",
      "status": "live",
      "priority": "P1"
    },
    {
      "rink_id": "dc_ashburn",
      "name": "Ashburn Ice House",
      "region": "DC Metro",
      "platform": "daysmart",
      "platform_code": "DS1",
      "scraper_file": "api/schedule.js",
      "company": "ashburn",
      "status": "live",
      "priority": "P1"
    },
    {
      "rink_id": "dc_ion",
      "name": "ION Training Center",
      "region": "DC Metro",
      "platform": "daysmart",
      "platform_code": "DS1",
      "scraper_file": "api/schedule.js",
      "company": "ionitc",
      "status": "live",
      "priority": "P1"
    },
    {
      "rink_id": "dc_haymarket",
      "name": "Haymarket Iceplex",
      "region": "DC Metro",
      "platform": "daysmart",
      "platform_code": "DS1",
      "scraper_file": "api/schedule.js",
      "company": "haymarketiceplex",
      "company_note": "Slug needs browser verification. Try haymarketiceplex first, then haymarket",
      "status": "planned",
      "priority": "P2",
      "last_verified": "2026-04-05",
      "notes": "Migrated from SportsEngine to DaySmart June 2025. Entire domain blocks server fetches \u2014 slug must be verified at apps.daysmartrecreation.com/dash/x/#/online/haymarketiceplex/event-registration"
    },
    {
      "rink_id": "dc_princeWilliam",
      "name": "Prince William Ice Center",
      "region": "DC Metro",
      "platform": "frontline",
      "platform_code": "FL1",
      "scraper_file": "api/scrape-frontline.js",
      "fac": "pwice",
      "facid": "1",
      "schedule_url": "https://www.frontline-connect.com/scheduleselect.cfm?fac=pwice&facid=1",
      "status": "planned",
      "priority": "P2",
      "last_verified": "2026-04-05",
      "notes": "SE page links directly to Frontline. Same platform as Flynn Rink. fac=pwice confirmed."
    },
    {
      "rink_id": "md_rockville",
      "name": "Rockville Ice Arena",
      "region": "DC Metro",
      "platform": "static-html",
      "platform_code": "SH1",
      "scraper_file": "api/scrape-statichtml.js",
      "strategy": "fixed-weekly",
      "schedule_url": "https://www.rockvilleicearena.com/page/show/2944804-public-and-stick-time-ice-schedules",
      "schedule": {
        "Mon": [
          {
            "name": "Public Skating",
            "type": "public",
            "start": "12:00",
            "end": "14:00"
          }
        ],
        "Wed": [
          {
            "name": "Public Skating",
            "type": "public",
            "start": "12:00",
            "end": "14:00"
          }
        ],
        "Fri": [
          {
            "name": "Public Skating",
            "type": "public",
            "start": "12:00",
            "end": "14:00"
          }
        ]
      },
      "stick_price": 18.0,
      "status": "planned",
      "priority": "P2",
      "last_verified": "2026-04-05",
      "notes": "SE blocks server scraping. Schedule confirmed Mon/Wed/Fri 12-2pm. Stick Time $18/goalies free. Verify full current times before deploying."
    },
    {
      "rink_id": "dc_fairfax",
      "name": "Fairfax Ice Arena",
      "region": "DC Metro",
      "platform": "static-html",
      "platform_code": "SH1",
      "scraper_file": "api/scrape-fairfax.js",
      "status": "live",
      "priority": "P1"
    },
    {
      "rink_id": "dc_loudoun",
      "name": "Loudoun Ice Centre",
      "region": "DC Metro",
      "platform": "wellnessliving",
      "platform_code": "WL1",
      "scraper_file": "api/scrape-wellnessliving.js",
      "status": "planned",
      "priority": "P2"
    },
    {
      "rink_id": "dc_mountVernon",
      "name": "Mount Vernon RECenter",
      "region": "DC Metro",
      "platform": "civicplus",
      "platform_code": "CV1",
      "scraper_file": "api/scrape-fairfaxcounty.js",
      "status": "planned",
      "priority": "P2"
    },
    {
      "rink_id": "md_cabinJohn",
      "name": "Cabin John Ice Rink",
      "region": "DC Metro",
      "platform": "civicplus",
      "platform_code": "CV2",
      "scraper_file": "api/scrape-montgomerycounty.js",
      "status": "planned",
      "priority": "P2"
    },
    {
      "rink_id": "md_wheaton",
      "name": "Wheaton Ice Arena",
      "region": "DC Metro",
      "platform": "civicplus",
      "platform_code": "CV2",
      "scraper_file": "api/scrape-montgomerycounty.js",
      "status": "planned",
      "priority": "P2"
    },
    {
      "rink_id": "md_tucker",
      "name": "Tucker Road Ice Rink",
      "region": "DC Metro",
      "platform": "civicplus",
      "platform_code": "CV3",
      "scraper_file": "api/scrape-pgcounty.js",
      "status": "planned",
      "priority": "P2"
    },
    {
      "rink_id": "md_bowie",
      "name": "Bowie Ice Arena",
      "region": "DC Metro",
      "platform": "civicplus",
      "platform_code": "CV3",
      "scraper_file": "api/scrape-pgcounty.js",
      "status": "planned",
      "priority": "P2"
    },
    {
      "rink_id": "md_gardens",
      "name": "The Gardens Ice House",
      "region": "DC Metro",
      "platform": "unknown",
      "platform_code": "UN0",
      "scraper_file": "TBD",
      "status": "needs_audit",
      "priority": "P2"
    },
    {
      "rink_id": "sd_sdia",
      "name": "San Diego Ice Arena",
      "region": "San Diego",
      "platform": "daysmart",
      "platform_code": "DS1",
      "scraper_file": "api/schedule.js",
      "company": "sdia",
      "status": "live",
      "priority": "P1"
    },
    {
      "rink_id": "sd_poway",
      "name": "Poway ICE",
      "region": "San Diego",
      "platform": "daysmart",
      "platform_code": "DS2",
      "scraper_file": "api/schedule.js",
      "company": "rinks",
      "facility_id": 4,
      "facility_filter": "poway",
      "status": "live",
      "priority": "P1"
    },
    {
      "rink_id": "sd_utcice",
      "name": "UTC Ice Sports Center",
      "region": "San Diego",
      "platform": "bondsports",
      "platform_code": "BD1",
      "scraper_file": "api/scrape-bondsports.js",
      "org_id": 6884,
      "season_id": 68912,
      "status": "planned",
      "priority": "P1"
    },
    {
      "rink_id": "sd_kroc",
      "name": "Kroc Center Ice",
      "region": "San Diego",
      "platform": "salesforce",
      "platform_code": "SF1",
      "scraper_file": "api/scrape-kroc.js",
      "schedule_url": "https://sd.kroccommunity.org/s/registration",
      "website": "https://sd.kroccenter.org",
      "status": "planned",
      "priority": "P1"
    },
    {
      "rink_id": "sd_carlsbad",
      "name": "Ice Realm Carlsbad",
      "region": "San Diego",
      "platform": "google-calendar",
      "platform_code": "GC1",
      "scraper_file": "api/scrape-googlecal.js",
      "calendar_id": "07f8ijpg2mj92i9ka8dnlooctu5rqo3f@import.calendar.google.com",
      "status": "planned",
      "priority": "P1"
    },
    {
      "rink_id": "sd_skating_sea",
      "name": "Skating by the Sea",
      "region": "San Diego",
      "platform": "static-html",
      "platform_code": "SH1",
      "scraper_file": "api/scrape-skatingbythesea.js",
      "season_start": {
        "month": 11,
        "day": 21
      },
      "season_end": {
        "month": 1,
        "day": 4
      },
      "status": "live",
      "priority": "P2"
    },
    {
      "rink_id": "sd_iceoplex",
      "name": "Iceoplex at Escondido",
      "region": "San Diego",
      "platform": "closed",
      "platform_code": "N/A",
      "status": "closed",
      "priority": "P0",
      "notes": "Permanently closed July 2020. Remove from site."
    },
    {
      "rink_id": "la_anaheim",
      "name": "Anaheim ICE",
      "region": "Los Angeles",
      "platform": "daysmart",
      "platform_code": "DS2",
      "scraper_file": "api/schedule.js",
      "company": "rinks",
      "facility_id": 2,
      "facility_filter": "ai-",
      "status": "live",
      "priority": "P1"
    },
    {
      "rink_id": "la_greatpark",
      "name": "Great Park Ice",
      "region": "Los Angeles",
      "platform": "daysmart",
      "platform_code": "DS2",
      "scraper_file": "api/schedule.js",
      "company": "rinks",
      "facility_id": 1,
      "facility_filter": "gpi",
      "status": "live",
      "priority": "P1"
    },
    {
      "rink_id": "la_lakewood",
      "name": "Lakewood ICE",
      "region": "Los Angeles",
      "platform": "daysmart",
      "platform_code": "DS2",
      "scraper_file": "api/schedule.js",
      "company": "rinks",
      "facility_id": 3,
      "facility_filter": "li-",
      "status": "live",
      "priority": "P1"
    },
    {
      "rink_id": "la_yorbalinda",
      "name": "Yorba Linda ICE",
      "region": "Los Angeles",
      "platform": "daysmart",
      "platform_code": "DS2",
      "scraper_file": "api/schedule.js",
      "company": "rinks",
      "facility_id": 6,
      "facility_filter": "yorba",
      "status": "live",
      "priority": "P1"
    },
    {
      "rink_id": "la_khs",
      "name": "KHS Ice",
      "region": "Los Angeles",
      "platform": "daysmart",
      "platform_code": "DS2",
      "scraper_file": "api/schedule.js",
      "company": "rinks",
      "facility_id": 9,
      "facility_filter": "khs",
      "status": "live",
      "priority": "P1"
    },
    {
      "rink_id": "ri_risports",
      "name": "Rhode Island Sports Center",
      "region": "Providence",
      "platform": "daysmart",
      "platform_code": "DS1",
      "scraper_file": "api/schedule.js",
      "company": "risportscenter",
      "status": "live",
      "priority": "P1"
    },
    {
      "rink_id": "ri_smithfield",
      "name": "Smithfield Municipal Ice Rink",
      "region": "Providence",
      "platform": "static-html",
      "platform_code": "SH1",
      "scraper_file": "api/scrape-statichtml.js",
      "strategy": "fixed-weekly",
      "schedule_url": "https://www.smithfieldri.gov/departments/ice-rink/information-and-rates",
      "status": "live",
      "priority": "P1"
    },
    {
      "rink_id": "ri_benny",
      "name": "Benny Magiera Rink",
      "region": "Providence",
      "platform": "civicplus",
      "platform_code": "SH1",
      "scraper_file": "api/scrape-statichtml.js",
      "strategy": "civicplus",
      "schedule_url": "https://www.westwarwickri.org/calendar.aspx",
      "status": "live",
      "priority": "P1",
      "notes": "Schedule posted weekly \u2014 NOT fixed. Fetched live from CivicPlus."
    },
    {
      "rink_id": "ri_thayer",
      "name": "Thayer Arena",
      "region": "Providence",
      "platform": "civicplus",
      "platform_code": "CV4",
      "scraper_file": "api/scrape-warwickri.js",
      "status": "planned",
      "priority": "P2"
    },
    {
      "rink_id": "ri_cranston",
      "name": "Cranston Veterans Memorial Rink",
      "region": "Providence",
      "platform": "unknown",
      "platform_code": "UN0",
      "scraper_file": "TBD",
      "status": "needs_audit",
      "priority": "P2"
    },
    {
      "rink_id": "ri_dennis",
      "name": "Dennis Lynch Arena",
      "region": "Providence",
      "platform": "unknown",
      "platform_code": "UN0",
      "scraper_file": "TBD",
      "status": "needs_audit",
      "priority": "P2"
    },
    {
      "rink_id": "ri_boss",
      "name": "Boss Ice Arena (URI)",
      "region": "Providence",
      "platform": "unknown",
      "platform_code": "UN0",
      "scraper_file": "TBD",
      "status": "needs_audit",
      "priority": "P2"
    },
    {
      "rink_id": "ri_levy",
      "name": "Levy Community Ice Center",
      "region": "Providence",
      "platform": "unknown",
      "platform_code": "UN0",
      "scraper_file": "TBD",
      "status": "needs_audit",
      "priority": "P2"
    },
    {
      "rink_id": "ri_adelard",
      "name": "Adelard Arena",
      "region": "Providence",
      "platform": "unknown",
      "platform_code": "UN0",
      "scraper_file": "TBD",
      "status": "needs_audit",
      "priority": "P2"
    },
    {
      "rink_id": "ma_warrior",
      "name": "Warrior Ice Arena",
      "region": "Boston",
      "platform": "daysmart",
      "platform_code": "DS1",
      "scraper_file": "api/schedule.js",
      "company": "warriorice",
      "status": "live",
      "priority": "P1"
    },
    {
      "rink_id": "ma_babson",
      "name": "Babson Skating Center",
      "region": "Boston",
      "platform": "daysmart",
      "platform_code": "DS1",
      "scraper_file": "api/schedule.js",
      "company": "babson",
      "status": "live",
      "priority": "P1"
    },
    {
      "rink_id": "ma_breakaway",
      "name": "Breakaway Ice Center",
      "region": "Boston",
      "platform": "daysmart",
      "platform_code": "DS1",
      "scraper_file": "api/schedule.js",
      "company": "breakawayice",
      "status": "planned",
      "priority": "P2",
      "last_verified": "2026-04-05",
      "notes": "Slug confirmed from official Linktree (linktr.ee/bichockey). Was incorrectly coded SE1."
    },
    {
      "rink_id": "ma_flynn",
      "name": "Flynn Rink",
      "region": "Boston",
      "platform": "frontline",
      "platform_code": "FL1",
      "scraper_file": "api/scrape-frontline.js",
      "fac": "flynn",
      "schedule_url": "https://www.frontline-connect.com/scheduleselect.cfm?fac=flynn",
      "status": "planned",
      "priority": "P2",
      "notes": "Seasonal Oct\u2013April."
    },
    {
      "rink_id": "ma_steriti",
      "name": "Steriti Memorial Rink",
      "region": "Boston",
      "platform": "dcr",
      "platform_code": "DC1",
      "scraper_file": "api/scrape-dcr.js",
      "status": "planned",
      "priority": "P1"
    },
    {
      "rink_id": "ma_murphy",
      "name": "Murphy Memorial Skating Rink",
      "region": "Boston",
      "platform": "dcr",
      "platform_code": "DC1",
      "scraper_file": "api/scrape-dcr.js",
      "status": "planned",
      "priority": "P1"
    },
    {
      "rink_id": "ma_porrazzo",
      "name": "Porrazzo Skating Rink",
      "region": "Boston",
      "platform": "dcr",
      "platform_code": "DC1",
      "scraper_file": "api/scrape-dcr.js",
      "status": "planned",
      "priority": "P1"
    },
    {
      "rink_id": "ma_devine",
      "name": "Devine Memorial Rink",
      "region": "Boston",
      "platform": "dcr",
      "platform_code": "DC1",
      "scraper_file": "api/scrape-dcr.js",
      "status": "planned",
      "priority": "P1"
    },
    {
      "rink_id": "ma_reilly",
      "name": "Reilly Memorial Rink",
      "region": "Boston",
      "platform": "dcr",
      "platform_code": "DC1",
      "scraper_file": "api/scrape-dcr.js",
      "status": "planned",
      "priority": "P2"
    },
    {
      "rink_id": "ma_jimroche",
      "name": "Jim Roche Community Ice Arena",
      "region": "Boston",
      "platform": "fmc-ice-sports",
      "platform_code": "FM1",
      "scraper_file": "api/scrape-fmcice.js",
      "rink_url": "https://fmcicesports.com/rink/jim-roche-community-ice-arena",
      "status": "planned",
      "priority": "P2"
    },
    {
      "rink_id": "ma_driscoll",
      "name": "Driscoll Rink",
      "region": "Boston",
      "platform": "fmc-ice-sports",
      "platform_code": "FM1",
      "scraper_file": "api/scrape-fmcice.js",
      "rink_url": "https://fmcicesports.com/rink/fall-river-driscoll-skating-arena",
      "status": "planned",
      "priority": "P2",
      "notes": "Reclassified from SH1. Managed by FMC Ice Sports (DCR facility)."
    },
    {
      "rink_id": "ma_pirelli",
      "name": "Pirelli Veterans Arena",
      "region": "Boston",
      "platform": "fmc-ice-sports",
      "platform_code": "FM1",
      "scraper_file": "api/scrape-fmcice.js",
      "rink_url": "https://fmcicesports.com/rink/franklin-veterans-skating-arena",
      "halix_url": "https://fmc.myhalix.io/pages/publicskatingcalendars.franklin",
      "status": "planned",
      "priority": "P2",
      "notes": "Reclassified from SH1. Managed by FMC Ice Sports since 1992."
    },
    {
      "rink_id": "ma_daly",
      "name": "Daly Rink",
      "region": "Boston",
      "platform": "static-html",
      "platform_code": "SH1",
      "scraper_file": "api/scrape-statichtml.js",
      "strategy": "wordpress-mycal",
      "schedule_url": "https://www.dalyrink.org/calendar/",
      "status": "planned",
      "priority": "P1"
    },
    {
      "rink_id": "ma_burbank",
      "name": "Burbank Ice Arena",
      "region": "Boston",
      "platform": "static-html",
      "platform_code": "SH1",
      "scraper_file": "api/scrape-statichtml.js",
      "strategy": "fixed-weekly",
      "schedule_url": "https://www.burbankicearena.com/public-skating",
      "status": "planned",
      "priority": "P1"
    },
    {
      "rink_id": "ma_stoneham",
      "name": "Stoneham Arena",
      "region": "Boston",
      "platform": "static-html",
      "platform_code": "SH1",
      "scraper_file": "api/scrape-statichtml.js",
      "strategy": "civicplus",
      "schedule_url": "https://www.stoneham-ma.gov/calendar.aspx",
      "calendar_cid": "26",
      "status": "planned",
      "priority": "P1"
    },
    {
      "rink_id": "ma_loring",
      "name": "Loring Arena",
      "region": "Boston",
      "platform": "static-html",
      "platform_code": "SH1",
      "scraper_file": "api/scrape-statichtml.js",
      "strategy": "civicplus",
      "schedule_url": "https://www.framinghamma.gov/calendar.aspx",
      "status": "planned",
      "priority": "P2"
    },
    {
      "rink_id": "ma_norfolk",
      "name": "Norfolk Ice Arena",
      "region": "Boston",
      "platform": "static-html",
      "platform_code": "SH1",
      "scraper_file": "api/scrape-statichtml.js",
      "strategy": "fixed-weekly",
      "schedule_url": "https://norfolkarena.com/index.php/publicskating/",
      "status": "planned",
      "priority": "P2"
    },
    {
      "rink_id": "ma_ristuccia",
      "name": "Ristuccia Memorial Arena",
      "region": "Boston",
      "platform": "static-html",
      "platform_code": "SH1",
      "scraper_file": "api/scrape-statichtml.js",
      "strategy": "fixed-weekly",
      "schedule_url": "https://skatewilm.com/skating/public-sessions/public-skating-sessions/",
      "status": "planned",
      "priority": "P2",
      "notes": "ristucciaarena.com times out. Schedule confirmed from Skating Club of Wilmington: Wed 7:10pm, Fri 7:30pm, Sat+Sun 3:15pm."
    },
    {
      "rink_id": "ma_connell",
      "name": "Connell Memorial Rink",
      "region": "Boston",
      "platform": "static-html",
      "platform_code": "SH1",
      "scraper_file": "api/scrape-statichtml.js",
      "strategy": "fixed-weekly",
      "schedule_url": "https://weymouth.ma.us/DocumentCenter/View/562/Open-Skate-Schedule",
      "status": "planned",
      "priority": "P2",
      "notes": "PDF schedule. Fall 2025: Mon-Fri 10am-1:45pm, Sat 2:50pm, Sun 3pm. Verify PDF each season."
    },
    {
      "rink_id": "ma_mcvann",
      "name": "McVann-O'Keefe Rink",
      "region": "Boston",
      "platform": "static-html",
      "platform_code": "SH1",
      "scraper_file": "api/scrape-statichtml.js",
      "strategy": "fixed-weekly",
      "schedule_url": "https://peabodyskating.org",
      "status": "planned",
      "priority": "P2",
      "notes": "Site has live 2-week calendar \u2014 DevTools audit needed for hidden JSON endpoint. Fallback: Mon-Fri 10-11:45am, Sat 2pm, Sun 2:10pm, Fri 6:30pm."
    },
    {
      "rink_id": "ma_valleyrinks1",
      "name": "Northeast ISC at Valley Rinks",
      "region": "Boston",
      "platform": "valleyrinks",
      "platform_code": "VR1",
      "scraper_file": "api/scrape-valleyrinks.js",
      "status": "planned",
      "priority": "P2"
    },
    {
      "rink_id": "ma_chelmsford",
      "name": "Chelmsford Forum",
      "region": "Boston",
      "platform": "valleyrinks",
      "platform_code": "VR1",
      "scraper_file": "api/scrape-valleyrinks.js",
      "status": "planned",
      "priority": "P2"
    },
    {
      "rink_id": "ma_rodman",
      "name": "Cadillac of Norwood Ice Arena",
      "region": "Boston",
      "platform": "unknown",
      "platform_code": "UN0",
      "scraper_file": "TBD",
      "website": "https://cadillacicearena.com",
      "status": "needs_audit",
      "priority": "P2",
      "notes": "Formerly Rodman Arena. DevTools audit needed on cadillacicearena.com."
    },
    {
      "rink_id": "ma_hobomock",
      "name": "Hobomock Arena",
      "region": "Boston",
      "platform": "event-only",
      "platform_code": "UN0",
      "scraper_file": "TBD",
      "status": "low_priority",
      "priority": "P3",
      "notes": "No regular public skate. Events via Pilgrim Skating Club (pilgrimskatingclub.com). Skip scraper."
    },
    {
      "rink_id": "ma_foxboro",
      "name": "Foxboro Sports Center",
      "region": "Boston",
      "platform": "leagueapps",
      "platform_code": "LA1",
      "scraper_file": "TBD",
      "status": "low_priority",
      "priority": "P3"
    },
    {
      "rink_id": "dc_stJames",
      "name": "The St. James",
      "region": "DC Metro",
      "platform": "leagueapps",
      "platform_code": "LA1",
      "scraper_file": "TBD",
      "status": "low_priority",
      "priority": "P3"
    }
  ]
}